{
  "collections": {
    "quotes": {
      "day": {
        "author": "string",
        "text": "string",
        "timestamp": "timestamp"
      }
    },
    "users": {
      "userId": {
        "preferences": {},
        "days": {
          "number": 1,
          "timestamp": "timestamp",
          "archiveLists": {
            "daily": {
              "todoId": {
                "completed": false,
                "content": "string",
                "order": 0
              }
            },
            "priority": {
              "todoId": {
                "completed": false,
                "content": "string",
                "order": 0
              }
            },
            "listId": {
              "order": 0,
              "todos": {
                "todoId": {
                  "completed": false,
                  "content": "string",
                  "order": 0
                }
              }
            }
          }
        },
        "lists": {
          "daily": {
            "todoId": {
              "completed": false,
              "content": "string",
              "order": 0
            }
          },
          "priority": {
            "todoId": {
              "completed": false,
              "content": "string",
              "order": 0
            }
          },
          "listId": {
            "order": 0,
            "todos": {
              "todoId": {
                "completed": false,
                "content": "string",
                "order": 0
              }
            }
          }
        }
      }
    }
  }
}